.gitignore
MANIFEST.in
README.rst
setup.py
django_taobao.egg-info/PKG-INFO
django_taobao.egg-info/SOURCES.txt
django_taobao.egg-info/dependency_links.txt
django_taobao.egg-info/top_level.txt
taobao/__init__.py
taobao/admin.py
taobao/forms.py
taobao/models.py
taobao/setup.py
taobao/taobaoapi.py
taobao/urls.py
taobao/views.py
taobao/templates/__init__.py