Metadata-Version: 1.0
Name: django-taobao
Version: 0.2.6
Summary: Taobao SDK for django.
Home-page: https://github.com/jcouyang/django-taobao
Author: Jichao Ouyang
Author-email: oyanglulu@gmail.com
License: MIT
Keywords: django,taobao,oauth,api
Platform: UNKNOWN
